MANIFEST.in
README.md
setup.py
topsis/__init__.py
topsis/topsis.py
topsis_vaibhav_102203381.egg-info/PKG-INFO
topsis_vaibhav_102203381.egg-info/SOURCES.txt
topsis_vaibhav_102203381.egg-info/dependency_links.txt
topsis_vaibhav_102203381.egg-info/entry_points.txt
topsis_vaibhav_102203381.egg-info/requires.txt
topsis_vaibhav_102203381.egg-info/top_level.txt