Metadata-Version: 2.1
Name: topsis-vaibhav-102203381
Version: 1.0.3
Summary: A Python package to perform TOPSIS (Technique for Order Preference by Similarity to Ideal Solution)
Home-page: https://github.com/vaibhavgarg0307/topsis_vaibhavgarg_102203381
Author: Vaibhav garg
Author-email: vaibhavgarg032005@gmail.com
License: UNKNOWN
Platform: UNKNOWN
Classifier: Programming Language :: Python :: 3
Classifier: License :: OSI Approved :: MIT License
Classifier: Operating System :: OS Independent
Requires-Python: >=3.6
